[
  { "id": "book_001", "title": "蛤蟆先生去看心理医生", "author": "罗伯特·戴博德", "category": "心理学" },
  { "id": "book_002", "title": "被讨厌的勇气", "author": "岸见一郎、古贺史健", "category": "心理学" },
  { "id": "book_003", "title": "自卑与超越", "author": "阿尔弗雷德·阿德勒", "category": "心理学" },
  { "id": "book_004", "title": "社会心理学", "author": "戴维·迈尔斯", "category": "心理学" },
  { "id": "book_005", "title": "亲密关系", "author": "罗兰·米勒", "category": "心理学" },
  { "id": "book_006", "title": "影响力", "author": "罗伯特·西奥迪尼", "category": "心理学" },
  { "id": "book_007", "title": "思考，快与慢", "author": "丹尼尔·卡尼曼", "category": "心理学" },
  { "id": "book_008", "title": "爱的艺术", "author": "艾里希·弗洛姆", "category": "心理学" },
  { "id": "book_009", "title": "少有人走的路", "author": "M.斯科特·派克", "category": "心理学" },
  { "id": "book_010", "title": "我们内心的冲突", "author": "卡伦·霍妮", "category": "心理学" },
  { "id": "book_011", "title": "我们时代的神经症人格", "author": "卡伦·霍妮", "category": "心理学" },
  { "id": "book_012", "title": "人性的弱点", "author": "戴尔·卡耐基", "category": "心理学" },
  { "id": "book_013", "title": "梦的解析", "author": "西格蒙德·弗洛伊德", "category": "心理学" },
  { "id": "book_014", "title": "乌合之众", "author": "古斯塔夫·勒庞", "category": "心理学" },
  { "id": "book_015", "title": "情绪急救", "author": "盖伊·温奇", "category": "心理学" },
  { "id": "book_016", "title": "身体从未忘记", "author": "巴塞尔·范德考克", "category": "心理学" },
  { "id": "book_017", "title": "依恋三部曲：依恋", "author": "约翰·鲍尔比", "category": "心理学" },
  { "id": "book_018", "title": "卓有成效的管理者", "author": "彼得·德鲁克", "category": "商业/职场" },
  { "id": "book_019", "title": "从优秀到卓越", "author": "吉姆·柯林斯", "category": "商业/职场" },
  { "id": "book_020", "title": "基业长青", "author": "吉姆·柯林斯、杰里·波拉斯", "category": "商业/职场" },
  { "id": "book_021", "title": "创新者的窘境", "author": "克莱顿·克里斯坦森", "category": "商业/职场" },
  { "id": "book_022", "title": "定位", "author": "艾·里斯、杰克·特劳特", "category": "商业/职场" },
  { "id": "book_023", "title": "蓝海战略", "author": "W.钱·金、勒妮·莫博涅", "category": "商业/职场" },
  { "id": "book_024", "title": "精益创业", "author": "埃里克·莱斯", "category": "商业/职场" },
  { "id": "book_025", "title": "从0到1", "author": "彼得·蒂尔", "category": "商业/职场" },
  { "id": "book_026", "title": "原则", "author": "瑞·达利欧", "category": "商业/职场" },
  { "id": "book_027", "title": "高效能人士的七个习惯", "author": "史蒂芬·柯维", "category": "商业/职场" },
  { "id": "book_028", "title": "金字塔原理", "author": "芭芭拉·明托", "category": "商业/职场" },
  { "id": "book_029", "title": "学会提问", "author": "尼尔·布朗、斯图尔特·基利", "category": "商业/职场" },
  { "id": "book_030", "title": "深度工作", "author": "卡尔·纽波特", "category": "商业/职场" },
  { "id": "book_031", "title": "掌控习惯", "author": "詹姆斯·克利尔", "category": "商业/职场" },
  { "id": "book_032", "title": "关键对话", "author": "科里·帕特森等", "category": "商业/职场" },
  { "id": "book_033", "title": "OKR工作法", "author": "克里斯蒂娜·沃特克", "category": "商业/职场" },
  { "id": "book_034", "title": "启示录：打造用户喜爱的产品", "author": "Marty Cagan", "category": "商业/职场" },
  { "id": "book_035", "title": "非暴力沟通", "author": "马歇尔·卢森堡", "category": "沟通表达" },
  { "id": "book_036", "title": "好好说话", "author": "马东等", "category": "沟通表达" },
  { "id": "book_037", "title": "蔡康永的说话之道", "author": "蔡康永", "category": "沟通表达" },
  { "id": "book_038", "title": "沟通的艺术", "author": "罗纳德·阿德勒、拉塞尔·普罗科特", "category": "沟通表达" },
  { "id": "book_039", "title": "关键对话", "author": "科里·帕特森等", "category": "沟通表达" },
  { "id": "book_040", "title": "谈话的力量", "author": "艾伦·加纳", "category": "沟通表达" },
  { "id": "book_041", "title": "高难度谈话", "author": "道格拉斯·斯通、布鲁斯·佩顿、希拉·汉", "category": "沟通表达" },
  { "id": "book_042", "title": "演讲的力量", "author": "克里斯·安德森", "category": "沟通表达" },
  { "id": "book_043", "title": "故事思维", "author": "安妮特·西蒙斯", "category": "沟通表达" },
  { "id": "book_044", "title": "一本小小的红色写作书", "author": "布兰登·罗伊尔", "category": "沟通表达" },
  { "id": "book_045", "title": "金字塔原理", "author": "芭芭拉·明托", "category": "沟通表达" },
  { "id": "book_046", "title": "即兴演讲", "author": "朱迪思·汉弗莱", "category": "沟通表达" },
  { "id": "book_047", "title": "沟通的方法", "author": "脱不花", "category": "沟通表达" },
  { "id": "book_048", "title": "可复制的沟通力", "author": "樊登", "category": "沟通表达" },
  { "id": "book_049", "title": "影响力", "author": "罗伯特·西奥迪尼", "category": "沟通表达" },
  { "id": "book_050", "title": "学会提问", "author": "尼尔·布朗、斯图尔特·基利", "category": "沟通表达" },
  { "id": "book_051", "title": "也许你该找个人聊聊", "author": "洛莉·戈特利布", "category": "自我成长" },
  { "id": "book_052", "title": "了不起的我", "author": "陈海贤", "category": "自我成长" },
  { "id": "book_053", "title": "认知觉醒", "author": "周岭", "category": "自我成长" },
  { "id": "book_054", "title": "认知驱动", "author": "周岭", "category": "自我成长" },
  { "id": "book_055", "title": "拆掉思维里的墙", "author": "古典", "category": "自我成长" },
  { "id": "book_056", "title": "把时间当作朋友", "author": "李笑来", "category": "自我成长" },
  { "id": "book_057", "title": "精进", "author": "采铜", "category": "自我成长" },
  { "id": "book_058", "title": "刻意练习", "author": "安德斯·艾利克森、罗伯特·普尔", "category": "自我成长" },
  { "id": "book_059", "title": "终身成长", "author": "卡罗尔·德韦克", "category": "自我成长" },
  { "id": "book_060", "title": "心流", "author": "米哈里·契克森米哈赖", "category": "自我成长" },
  { "id": "book_061", "title": "反脆弱", "author": "纳西姆·尼古拉斯·塔勒布", "category": "自我成长" },
  { "id": "book_062", "title": "原则", "author": "瑞·达利欧", "category": "自我成长" },
  { "id": "book_063", "title": "掌控习惯", "author": "詹姆斯·克利尔", "category": "自我成长" },
  { "id": "book_064", "title": "拖延心理学", "author": "简·博克、莱诺拉·袁", "category": "自我成长" },
  { "id": "book_065", "title": "当下的力量", "author": "埃克哈特·托利", "category": "自我成长" },
  { "id": "book_066", "title": "被讨厌的勇气", "author": "岸见一郎、古贺史健", "category": "自我成长" },
  { "id": "book_067", "title": "蛤蟆先生去看心理医生", "author": "罗伯特·戴博德", "category": "自我成长" },
  { "id": "book_068", "title": "红楼梦", "author": "曹雪芹", "category": "经典文学" },
  { "id": "book_069", "title": "活着", "author": "余华", "category": "经典文学" },
  { "id": "book_070", "title": "许三观卖血记", "author": "余华", "category": "经典文学" },
  { "id": "book_071", "title": "平凡的世界", "author": "路遥", "category": "经典文学" },
  { "id": "book_072", "title": "围城", "author": "钱锺书", "category": "经典文学" },
  { "id": "book_073", "title": "骆驼祥子", "author": "老舍", "category": "经典文学" },
  { "id": "book_074", "title": "边城", "author": "沈从文", "category": "经典文学" },
  { "id": "book_075", "title": "百年孤独", "author": "加西亚·马尔克斯", "category": "经典文学" },
  { "id": "book_076", "title": "追风筝的人", "author": "卡勒德·胡赛尼", "category": "经典文学" },
  { "id": "book_077", "title": "月亮与六便士", "author": "毛姆", "category": "经典文学" },
  { "id": "book_078", "title": "局外人", "author": "阿尔贝·加缪", "category": "经典文学" },
  { "id": "book_079", "title": "1984", "author": "乔治·奥威尔", "category": "经典文学" },
  { "id": "book_080", "title": "动物农场", "author": "乔治·奥威尔", "category": "经典文学" },
  { "id": "book_081", "title": "小王子", "author": "安托万·德·圣-埃克苏佩里", "category": "经典文学" },
  { "id": "book_082", "title": "杀死一只知更鸟", "author": "哈珀·李", "category": "经典文学" },
  { "id": "book_083", "title": "傲慢与偏见", "author": "简·奥斯汀", "category": "经典文学" },
  { "id": "book_084", "title": "不能承受的生命之轻", "author": "米兰·昆德拉", "category": "经典文学" },
  { "id": "book_085", "title": "苏菲的世界", "author": "乔斯坦·贾德", "category": "哲学入门" },
  { "id": "book_086", "title": "哲学家们都干了些什么", "author": "林欣浩", "category": "哲学入门" },
  { "id": "book_087", "title": "大问题：简明哲学导论", "author": "罗伯特·所罗门、凯瑟琳·希金斯", "category": "哲学入门" },
  { "id": "book_088", "title": "西方哲学史", "author": "伯特兰·罗素", "category": "哲学入门" },
  { "id": "book_089", "title": "理想国", "author": "柏拉图", "category": "哲学入门" },
  { "id": "book_090", "title": "尼各马可伦理学", "author": "亚里士多德", "category": "哲学入门" },
  { "id": "book_091", "title": "沉思录", "author": "马可·奥勒留", "category": "哲学入门" },
  { "id": "book_092", "title": "查拉图斯特拉如是说", "author": "弗里德里希·尼采", "category": "哲学入门" },
  { "id": "book_093", "title": "存在与虚无", "author": "让-保罗·萨特", "category": "哲学入门" },
  { "id": "book_094", "title": "西西弗神话", "author": "阿尔贝·加缪", "category": "哲学入门" },
  { "id": "book_095", "title": "道德经", "author": "老子", "category": "哲学入门" },
  { "id": "book_096", "title": "庄子", "author": "庄子", "category": "哲学入门" },
  { "id": "book_097", "title": "论语", "author": "孔子及其弟子", "category": "哲学入门" },
  { "id": "book_098", "title": "中国哲学简史", "author": "冯友兰", "category": "哲学入门" },
  { "id": "book_099", "title": "人生的智慧", "author": "叔本华", "category": "哲学入门" },
  { "id": "book_100", "title": "论自由", "author": "约翰·斯图亚特·密尔", "category": "哲学入门" },
  { "id": "book_101", "title": "明朝那些事儿", "author": "当年明月", "category": "历史" },
  { "id": "book_102", "title": "万历十五年", "author": "黄仁宇", "category": "历史" },
  { "id": "book_103", "title": "中国大历史", "author": "黄仁宇", "category": "历史" },
  { "id": "book_104", "title": "全球通史", "author": "斯塔夫里阿诺斯", "category": "历史" },
  { "id": "book_105", "title": "人类简史", "author": "尤瓦尔·赫拉利", "category": "历史" },
  { "id": "book_106", "title": "枪炮、病菌与钢铁", "author": "贾雷德·戴蒙德", "category": "历史" },
  { "id": "book_107", "title": "丝绸之路：一部全新的世界史", "author": "彼得·弗兰科潘", "category": "历史" },
  { "id": "book_108", "title": "罗马人的故事", "author": "盐野七生", "category": "历史" },
  { "id": "book_109", "title": "耶路撒冷三千年", "author": "西蒙·蒙蒂菲奥里", "category": "历史" },
  { "id": "book_110", "title": "大国的兴衰", "author": "保罗·肯尼迪", "category": "历史" },
  { "id": "book_111", "title": "极简欧洲史", "author": "约翰·赫斯特", "category": "历史" },
  { "id": "book_112", "title": "叫魂：1768年中国妖术大恐慌", "author": "孔飞力", "category": "历史" },
  { "id": "book_113", "title": "剑桥中国史", "author": "费正清、崔瑞德等", "category": "历史" },
  { "id": "book_114", "title": "资治通鉴", "author": "司马光", "category": "历史" },
  { "id": "book_115", "title": "史记", "author": "司马迁", "category": "历史" },
  { "id": "book_116", "title": "魏晋南北朝史讲演录", "author": "陈寅恪", "category": "历史" },
  { "id": "book_117", "title": "隋唐制度渊源略论稿", "author": "陈寅恪", "category": "历史" },
  { "id": "book_118", "title": "苏东坡传", "author": "林语堂", "category": "传记" },
  { "id": "book_119", "title": "曾国藩传", "author": "张宏杰", "category": "传记" },
  { "id": "book_120", "title": "王阳明大传", "author": "冈田武彦", "category": "传记" },
  { "id": "book_121", "title": "邓小平时代", "author": "傅高义", "category": "传记" },
  { "id": "book_122", "title": "毛泽东传", "author": "菲利普·肖特", "category": "传记" },
  { "id": "book_123", "title": "乔布斯传", "author": "沃尔特·艾萨克森", "category": "传记" },
  { "id": "book_124", "title": "埃隆·马斯克传", "author": "沃尔特·艾萨克森", "category": "传记" },
  { "id": "book_125", "title": "爱因斯坦传", "author": "沃尔特·艾萨克森", "category": "传记" },
  { "id": "book_126", "title": "富兰克林传", "author": "沃尔特·艾萨克森", "category": "传记" },
  { "id": "book_127", "title": "列奥纳多·达·芬奇传", "author": "沃尔特·艾萨克森", "category": "传记" },
  { "id": "book_128", "title": "鞋狗", "author": "菲尔·奈特", "category": "传记" },
  { "id": "book_129", "title": "成为", "author": "米歇尔·奥巴马", "category": "传记" },
  { "id": "book_130", "title": "阿加西自传", "author": "安德烈·阿加西", "category": "传记" },
  { "id": "book_131", "title": "一个瑜伽行者的自传", "author": "帕拉宏撒·尤迦南达", "category": "传记" },
  { "id": "book_132", "title": "当呼吸化为空气", "author": "保罗·卡拉尼什", "category": "传记" },
  { "id": "book_133", "title": "你当像鸟飞往你的山", "author": "塔拉·韦斯特弗", "category": "传记" },
  { "id": "book_134", "title": "小狗钱钱", "author": "博多·舍费尔", "category": "财商入门" },
  { "id": "book_135", "title": "富爸爸穷爸爸", "author": "罗伯特·清崎", "category": "财商入门" },
  { "id": "book_136", "title": "穷查理宝典", "author": "查理·芒格", "category": "财商入门" },
  { "id": "book_137", "title": "聪明的投资者", "author": "本杰明·格雷厄姆", "category": "财商入门" },
  { "id": "book_138", "title": "证券分析", "author": "本杰明·格雷厄姆、大卫·多德", "category": "财商入门" },
  { "id": "book_139", "title": "漫步华尔街", "author": "伯顿·马尔基尔", "category": "财商入门" },
  { "id": "book_140", "title": "投资最重要的事", "author": "霍华德·马克斯", "category": "财商入门" },
  { "id": "book_141", "title": "彼得·林奇的成功投资", "author": "彼得·林奇", "category": "财商入门" },
  { "id": "book_142", "title": "共同基金常识", "author": "约翰·博格", "category": "财商入门" },
  { "id": "book_143", "title": "邻家的百万富翁", "author": "托马斯·斯坦利、威廉·丹科", "category": "财商入门" },
  { "id": "book_144", "title": "金钱心理学", "author": "摩根·豪泽尔", "category": "财商入门" },
  { "id": "book_145", "title": "财务自由之路", "author": "博多·舍费尔", "category": "财商入门" },
  { "id": "book_146", "title": "巴比伦最富有的人", "author": "乔治·克拉森", "category": "财商入门" },
  { "id": "book_147", "title": "经济学原理", "author": "曼昆", "category": "财商入门" },
  { "id": "book_148", "title": "薛兆丰经济学讲义", "author": "薛兆丰", "category": "财商入门" },
  { "id": "book_149", "title": "逃不开的经济周期", "author": "拉斯·特维德", "category": "财商入门" },
  { "id": "book_150", "title": "原则", "author": "瑞·达利欧", "category": "财商入门" }
]
